mlguard/__init__.py
mlguard/bias_detecter.py
mlguard/class_imbalance.py
mlguard/multicollinearitychecker.py
mlguard/overfitting.py
mlguard/utils.py
mlguard-0.1.2.dist-info/LICENSE
mlguard-0.1.2.dist-info/METADATA
mlguard-0.1.2.dist-info/WHEEL
mlguard-0.1.2.dist-info/top_level.txt
mlguard-0.1.2.dist-info/RECORD
